flask_template_master/__init__.py
flask_template_master/compiler.py
flask_template_master/environments.py
flask_template_master/global_provider.py
flask_template_master/views.py
flask_template_master-0.1.0.dist-info/DESCRIPTION.rst
flask_template_master-0.1.0.dist-info/METADATA
flask_template_master-0.1.0.dist-info/RECORD
flask_template_master-0.1.0.dist-info/WHEEL
flask_template_master-0.1.0.dist-info/metadata.json
flask_template_master-0.1.0.dist-info/top_level.txt
