Metadata-Version: 2.0
Name: flask-template-master
Version: 0.1.0
Summary: A flask plugin to create a template render service
Home-page: https://github.com/AKuederle/flask-template-master
Author: Arne Küderle
Author-email: a.kuederle@gmail.com
License: UNKNOWN
Platform: UNKNOWN
Classifier: Programming Language :: Python :: 3.5
